numberfield_flet/__init__.py
numberfield_flet-1.0.0.dist-info/LICENSE
numberfield_flet-1.0.0.dist-info/METADATA
numberfield_flet-1.0.0.dist-info/WHEEL
numberfield_flet-1.0.0.dist-info/top_level.txt
numberfield_flet-1.0.0.dist-info/RECORD
