Metadata-Version: 2.1
Name: numberfield-flet
Version: 1.0.0
Summary: A custom Flet TextField that only accepts numerical input (int or float).
Author-email: FanaticExplorer <andrey.gurtov@gmail.com>
License: MIT
Project-URL: Homepage, https://github.com/FanaticExplorer/FletNumberField
Classifier: Programming Language :: Python :: 3
Classifier: License :: OSI Approved :: MIT License
Classifier: Operating System :: OS Independent
Requires-Python: >=3.8
License-File: LICENSE
Requires-Dist: flet
